{
  "name" : "Sea Serpent",
  "gender" : "Male",
  "race" : "LargeAnimal",
  "script" : "ai/aiStandard",
  "icon" : {
    "sprite" : "creatures/serpent",
    "color" : "#ffffffff"
  },
  "attributes" : {
    "strength" : 17,
    "dexterity" : 20,
    "constitution" : 15,
    "intelligence" : 3,
    "wisdom" : 5,
    "charisma" : 9
  },
  "skills" : {

  },
  "abilities" : [
    {
      "id" : "NaturalArmor5",
      "levelObtained" : 1
    }
  ],
  "roles" : {
    "Monster" : 11
  },
  "inventory" : {
    "equipped" : {
      "MainHand" : {
        "id" : "unarmedLargeThreatens",
        "quality" : "Superb"
      }
    },
    "unequipped" : [
      
    ]
  },
  "reward" : [
    2000, 3000
  ],
  "loot" : [
    {
      "id" : "LootLevel5",
      "probability" : {
        "value" : 25,
        "mode" : "PerList"
      }
    }
  ]
}